caesar/__init__.py
caesar/__main__.py
caesar/cipher.py
caesar/cli.py
caesar_cli-0.1.dist-info/licenses/LICENSE.txt
caesar_cli-0.1.dist-info/METADATA
caesar_cli-0.1.dist-info/WHEEL
caesar_cli-0.1.dist-info/entry_points.txt
caesar_cli-0.1.dist-info/top_level.txt
caesar_cli-0.1.dist-info/RECORD
