Metadata-Version: 2.4
Name: caesar-cli
Version: 0.1
Summary: A Caesar Cipher encryption and decryption program
Home-page: https://github.com/ftkovr9k/caesar-cli
Author: Farhan Khan
Author-email: ftkover9k@gmail.com
Classifier: Programming Language :: Python :: 3.13
Classifier: License :: OSI Approved :: MIT License
Classifier: Operating System :: OS Independent
Requires-Python: >=3.13
License-File: LICENSE.txt
Dynamic: author
Dynamic: author-email
Dynamic: classifier
Dynamic: description
Dynamic: description-content-type
Dynamic: home-page
Dynamic: license-file
Dynamic: requires-python
Dynamic: summary
